syncoder/__init__.py
syncoder/codec.py
syncoder-0.0.0.dist-info/METADATA
syncoder-0.0.0.dist-info/WHEEL
syncoder-0.0.0.dist-info/licenses/LICENSE
syncoder-0.0.0.dist-info/RECORD
