Metadata-Version: 2.4
Name: syncoder
Version: 0.0.0
Summary: A codec for DNA data storage
Project-URL: Homepage, https://example.com/TBD
Project-URL: Issues, https://example.com/TBD/issues
Author-email: Christopher Takahashi <cnt@uw.edu>
License-Expression: BSD-3-Clause
License-File: LICENSE
Requires-Python: >=3.9
